{
  "tri": {
    "pos": {
      "x": 21,
      "y": 280
    },
    "ang": 0
  },
  "g": [
    {
      "x": 978,
      "y": 3
    },
    {
      "x": 975,
      "y": 599
    },
    {
      "x": 999,
      "y": 600
    },
    {
      "x": 998,
      "y": 0
    }
  ],
  "p": [
    [
      {
        "x": 131,
        "y": 2
      },
      {
        "x": 126,
        "y": 193
      },
      {
        "x": 181,
        "y": 195
      },
      {
        "x": 185,
        "y": 2
      }
    ],
    [
      {
        "x": 131,
        "y": 377
      },
      {
        "x": 171,
        "y": 378
      },
      {
        "x": 168,
        "y": 601
      },
      {
        "x": 129,
        "y": 599
      }
    ],
    [
      {
        "x": 501,
        "y": 70
      },
      {
        "x": 546,
        "y": 71
      },
      {
        "x": 544,
        "y": 525
      },
      {
        "x": 503,
        "y": 522
      }
    ]
  ]
}
